notedown/__init__.py
notedown/contentsmanager.py
notedown/main.py
notedown/notedown.py
notedown/templates/markdown.tpl
notedown/templates/markdown_outputs.tpl
mu_notedown-2.0.3.dist-info/LICENSE
mu_notedown-2.0.3.dist-info/METADATA
mu_notedown-2.0.3.dist-info/WHEEL
mu_notedown-2.0.3.dist-info/entry_points.txt
mu_notedown-2.0.3.dist-info/top_level.txt
mu_notedown-2.0.3.dist-info/RECORD
