Metadata-Version: 2.1
Name: mu-notedown
Version: 2.0.3
Summary: A fork of notedown
Home-page: http://github.com/mli/notedown
Author: Mu Li
Author-email: muli.cmu@gmail.com
License: BSD 2-Clause
Platform: UNKNOWN
Requires-Dist: nbformat
Requires-Dist: nbconvert
Requires-Dist: pandoc-attributes
Requires-Dist: six
